pyproject.toml
setup.py
vector_khing/__init__.py
vector_khing/vec2d.py
vector_khing.egg-info/PKG-INFO
vector_khing.egg-info/SOURCES.txt
vector_khing.egg-info/dependency_links.txt
vector_khing.egg-info/top_level.txt